LICENSE
MANIFEST.in
README.md
extradeco.py
setup.cfg
setup.py
extradeco.egg-info/PKG-INFO
extradeco.egg-info/SOURCES.txt
extradeco.egg-info/dependency_links.txt
extradeco.egg-info/top_level.txt