Metadata-Version: 1.1
Name: extradeco
Version: 0.1.1
Summary: Decorator utils. Currently 'paremetrized': a decorator to enable flat decorators: call the wrapped func straight from your decorator body
Home-page: https://github.com/jsbueno/extradeco
Author: João S. O. Bueno
Author-email: gwidion@gmail.com
License: LGPLv3+
Keywords: decorator utils simplifier
Platform: UNKNOWN
Classifier: Development Status :: 3 - Alpha
Classifier: Intended Audience :: Developers
Classifier: Programming Language :: Python :: 3.3
Classifier: Programming Language :: Python :: 3.4
Classifier: Programming Language :: Python :: 3.5
Classifier: License :: OSI Approved :: GNU Lesser General Public License v3 or later (LGPLv3+)
Classifier: License :: OSI Approved :: GNU General Public License v3 or later (GPLv3+)
Classifier: Operating System :: OS Independent
